plain/pages/CHANGELOG.md
plain/pages/README.md
plain/pages/__init__.py
plain/pages/config.py
plain/pages/default_settings.py
plain/pages/exceptions.py
plain/pages/markdown.py
plain/pages/pages.py
plain/pages/registry.py
plain/pages/urls.py
plain/pages/views.py
plain/pages/templates/page.html
plain_pages-0.16.1.dist-info/METADATA
plain_pages-0.16.1.dist-info/WHEEL
plain_pages-0.16.1.dist-info/licenses/LICENSE
plain_pages-0.16.1.dist-info/RECORD
