Metadata-Version: 2.4
Name: plain.pages
Version: 0.16.1
Summary: Serve static pages, markdown, and assets from templates/pages directories.
Author-email: Dave Gaeddert <dave.gaeddert@dropseed.dev>
License-Expression: BSD-3-Clause
License-File: LICENSE
Requires-Python: >=3.13
Requires-Dist: mistune>=3.0.0
Requires-Dist: plain<1.0.0
Requires-Dist: pygments>=2.0.0
Requires-Dist: python-frontmatter>=1.0.0
